flake8_pie/__init__.py
flake8_pie/base.py
flake8_pie/pie781_assign_and_return.py
flake8_pie/pie783_celery_explicit_names.py
flake8_pie/pie784_celery_crontab_args.py
flake8_pie/pie785_celery_require_tasks_expire.py
flake8_pie/pie786_precise_exception_handler.py
flake8_pie/pie787_no_len_condition.py
flake8_pie/pie788_no_bool_condition.py
flake8_pie/pie789_prefer_isinstance_type_compare.py
flake8_pie/pie790_no_unnecessary_pass.py
flake8_pie/pie791_no_pointless_statements.py
flake8_pie/pie792_no_inherit_object.py
flake8_pie/pie793_prefer_dataclass.py
flake8_pie/pie794_dupe_class_field_definitions.py
flake8_pie/pie795_prefer_stdlib_enums.py
flake8_pie/pie796_prefer_unique_enums.py
flake8_pie/pie797_no_unnecessary_if_expr.py
flake8_pie/pie798_no_unnecessary_class.py
flake8_pie/pie799_prefer_col_init.py
flake8_pie/pie800_no_unnecessary_spread.py
flake8_pie/pie801_prefer_simple_return.py
flake8_pie/pie802_prefer_simple_any_all.py
flake8_pie/pie803_prefer_logging_interpolation.py
flake8_pie/pie804_no_unnecessary_dict_kwargs.py
flake8_pie/pie805_prefer_literal.py
flake8_pie/pie806_no_assert_except.py
flake8_pie/pie807_pefer_list_builtin.py
flake8_pie/pie808_prefer_simple_range.py
flake8_pie/pie809_django_prefer_bulk.py
flake8_pie/test_utils.py
flake8_pie/tests/__init__.pyi
flake8_pie/tests/test_pie781_assign_and_return.py
flake8_pie/tests/test_pie783_celery_explicit_names.py
flake8_pie/tests/test_pie784_celery_crontab_args.py
flake8_pie/tests/test_pie785_celery_require_tasks_expire.py
flake8_pie/tests/test_pie786_precise_exception_handler.py
flake8_pie/tests/test_pie787_no_len_condition.py
flake8_pie/tests/test_pie788_no_bool_condition.py
flake8_pie/tests/test_pie789_prefer_isinstance_type_compare.py
flake8_pie/tests/test_pie790_no_unnecessary_pass.py
flake8_pie/tests/test_pie791_no_pointless_statements.py
flake8_pie/tests/test_pie792_no_inherit_object.py
flake8_pie/tests/test_pie793_prefer_dataclass.py
flake8_pie/tests/test_pie794_dupe_class_field_definitions.py
flake8_pie-0.15.0.dist-info/entry_points.txt
flake8_pie-0.15.0.dist-info/WHEEL
flake8_pie-0.15.0.dist-info/METADATA
flake8_pie-0.15.0.dist-info/RECORD
