Metadata-Version: 2.1
Name: flake8-pie
Version: 0.15.0
Summary: A flake8 extension that implements misc. lints
Home-page: https://github.com/sbdchd/flake8-pie
License: BSD-2-Clause
Keywords: flake8,lint
Author: Steve Dignam
Author-email: steve@dignam.xyz
Requires-Python: >=3.7
Classifier: Environment :: Console
Classifier: Intended Audience :: Developers
Classifier: License :: OSI Approved :: BSD License
Classifier: Operating System :: OS Independent
Classifier: Programming Language :: Python :: 3
Classifier: Programming Language :: Python :: 3.6
Classifier: Programming Language :: Python :: 3.7
Classifier: Topic :: Software Development :: Quality Assurance
Requires-Dist: typing_extensions
Project-URL: Repository, https://github.com/sbdchd/flake8-pie
